{
  "project_info": {
    "project_number": "820611046383",
    "firebase_url": "https://ikpmd-c8abf.firebaseio.com",
    "project_id": "ikpmd-c8abf",
    "storage_bucket": "ikpmd-c8abf.appspot.com"
  },
  "client": [
    {
      "client_info": {
        "mobilesdk_app_id": "1:820611046383:android:b1a03d9b8ecb912d",
        "android_client_info": {
          "package_name": "nl.hsleiden.basenstefan.ikpmd"
        }
      },
      "oauth_client": [
        {
          "client_id": "820611046383-odkpi2jn6at1qe9tjmlcjmec7h0hak03.apps.googleusercontent.com",
          "client_type": 1,
          "android_info": {
            "package_name": "nl.hsleiden.basenstefan.ikpmd",
            "certificate_hash": "d7da703ad5b764d90a7e16f9fa6f69386478ef09"
          }
        },
        {
          "client_id": "820611046383-toq751tt31lb5igqfja0vaqaos368b05.apps.googleusercontent.com",
          "client_type": 1,
          "android_info": {
            "package_name": "nl.hsleiden.basenstefan.ikpmd",
            "certificate_hash": "80d6359bb2125fa95b5d1d75456a90a43b47698c"
          }
        }
      ],
      "api_key": [
        {
          "current_key": "AIzaSyAHNGcwL5IXT5HfQOpDrFIxzzBSid1M8C8"
        }
      ],
      "services": {
        "appinvite_service": {
          "other_platform_oauth_client": [
            {
              "client_id": "820611046383-u45nd4cvlkf0bqcfbssvdhial4knvt3c.apps.googleusercontent.com",
              "client_type": 3
            }
          ]
        }
      }
    }
  ],
  "configuration_version": "1"
}